poetry_hello_world/__init__.py
poetry_hello_world/main.py
poetry_hello_world-0.1.0.dist-info/entry_points.txt
poetry_hello_world-0.1.0.dist-info/WHEEL
poetry_hello_world-0.1.0.dist-info/METADATA
poetry_hello_world-0.1.0.dist-info/RECORD
