Metadata-Version: 2.1
Name: poetry-hello-world
Version: 0.1.0
Summary: Hello World
Author: hideaki murotani
Author-email: munroyello@gmail.com
Requires-Python: >=3.7,<4.0
Classifier: Programming Language :: Python :: 3
Classifier: Programming Language :: Python :: 3.7
Classifier: Programming Language :: Python :: 3.8
